ntt_api_management/__init__.py
ntt_api_management/i_ntt_api.py
ntt_api_management/ntt_api_base.py
ntt_api_management/ntt_api_management.py
tests/__init__.py
tests/api_management_daily_limit_test.py
tests/api_management_minute_limit_test.py
tests/ntt_daily_limit_api.py
tests/ntt_minute_limit_api.py
ntt_api_management-1.0.0.dist-info/LICENSE
ntt_api_management-1.0.0.dist-info/METADATA
ntt_api_management-1.0.0.dist-info/WHEEL
ntt_api_management-1.0.0.dist-info/top_level.txt
ntt_api_management-1.0.0.dist-info/RECORD
