Metadata-Version: 2.1
Name: ntt-api-management
Version: 1.0.0
Summary: # ntt-api-management
Author: threezinedine
Author-email: threezinedine@gmail.com
Keywords: API,Management,ntt
License-File: LICENSE
